<PAMDataset>
  <Metadata>
    <MDI key="DataType">Generic</MDI>
  </Metadata>
  <Metadata domain="Esri">
    <MDI key="PyramidResamplingType">NEAREST</MDI>
  </Metadata>
  <PAMRasterBand band="1">
    <Histograms>
      <HistItem>
        <HistMin>0</HistMin>
        <HistMax>36.61970901489258</HistMax>
        <BucketCount>256</BucketCount>
        <IncludeOutOfRange>1</IncludeOutOfRange>
        <Approximate>0</Approximate>
        <HistCounts>1828|2776|2858|2944|2890|3017|2883|2943|2941|3006|2979|2939|3017|2961|2966|2808|3003|2974|2977|3053|2957|2912|2860|2867|2758|2807|2862|2891|2974|2898|2977|2925|2925|2941|2944|2922|2788|2712|2568|2562|2560|2520|2348|2273|2247|2352|2365|2256|2399|2382|2358|2513|2473|2439|2589|2697|2662|2768|2930|2890|2895|2898|2826|2875|2720|2711|2766|2829|2863|2745|2811|2776|2745|2624|2612|2748|2734|2681|2687|2717|2889|2898|2936|3267|2926|2875|2935|3031|2977|2994|3104|3039|2858|2973|3026|3172|3072|3149|3234|3208|3254|3214|3253|3138|2937|2964|2781|2660|2671|2726|2543|2574|2402|2324|2240|2032|1935|1811|1720|1692|1491|1453|1420|1305|1435|1306|1370|1304|1345|1341|1347|1349|1452|1441|1412|1395|1343|1307|1386|1325|1265|1257|1246|1185|1130|1144|1049|1078|1089|1056|977|948|982|845|800|754|730|694|707|720|665|707|686|650|639|628|593|614|553|571|566|591|524|514|515|493|488|439|443|447|389|393|356|324|360|330|366|368|359|388|381|383|366|364|316|324|319|385|419|358|288|305|309|283|307|304|273|271|298|291|263|241|268|225|339|337|318|324|288|280|310|2302|1939|1178|1314|2776|3221|3826|2615|2164|1786|1729|2105|2328|3237|6505|4810|5038|3663|847|809|889|1025|1378|1246|1246|1181|924|881|882|961|556|510|906|930|1</HistCounts>
      </HistItem>
    </Histograms>
    <Metadata>
      <MDI key="SourceBandIndex">0</MDI>
      <MDI key="STATISTICS_COVARIANCES">106.7367933841965</MDI>
      <MDI key="STATISTICS_EXCLUDEDVALUES"></MDI>
      <MDI key="STATISTICS_MAXIMUM">36.619709014893</MDI>
      <MDI key="STATISTICS_MEAN">14.224826372734</MDI>
      <MDI key="STATISTICS_MINIMUM">0</MDI>
      <MDI key="STATISTICS_SKIPFACTORX">1</MDI>
      <MDI key="STATISTICS_SKIPFACTORY">1</MDI>
      <MDI key="STATISTICS_STDDEV">10.331350027184</MDI>
    </Metadata>
  </PAMRasterBand>
</PAMDataset>
